{
  "dateCreated": "2024-07-19T13:36:27.341Z",
  "tracks": [
    {
      "trackId": "SN75752_sorted.gff",
      "attributesIndexed": [
        "name",
        "gene",
        "locus_tag"
      ],
      "excludedTypes": [
        "CDS",
        "exon",
        "id"
      ],
      "adapterConf": {
        "type": "Gff3TabixAdapter",
        "gffGzLocation": {
          "locationType": "UriLocation",
          "uri": "data/SN75752/SN75752_sorted.gff.gz"
        },
        "index": {
          "location": {
            "locationType": "UriLocation",
            "uri": "data/SN75752/SN75752_sorted.gff.gz.tbi"
          }
        }
      }
    }
  ],
  "assemblyNames": [
    "SN75752"
  ]
}